onhold/__init__.py
onhold/__main__.py
onhold/after.py
onhold/base.py
onhold/during.py
onhold-0.6.5.dist-info/LICENSE
onhold-0.6.5.dist-info/METADATA
onhold-0.6.5.dist-info/WHEEL
onhold-0.6.5.dist-info/entry_points.txt
onhold-0.6.5.dist-info/top_level.txt
onhold-0.6.5.dist-info/zip-safe
onhold-0.6.5.dist-info/RECORD
