Metadata-Version: 2.1
Name: onhold
Version: 0.6.5
Summary: 🔊 Play music while and after jobs complete
Home-page: https://github.com/alexdelorenzo/onhold
Author: Alex DeLorenzo
License: AGPL-3.0
Platform: UNKNOWN
Requires-Python: >=3.6
Requires-Dist: click (==7.1.2)
Requires-Dist: boombox (==0.56)
Requires-Dist: play-sounds (==0.4.1)
Requires-Dist: PyObjc (==6.2.2) ; sys_platform == "darwin"
